quizzical/__init__.py
quizzical/__main__.py
quizzical/app/__init__.py
quizzical/app/quizzical.py
quizzical/app/data/__init__.py
quizzical/app/data/locations.py
quizzical/app/data/quiz_parameters.py
quizzical/app/data/quizzes_file.py
quizzical/app/screens/__init__.py
quizzical/app/screens/confirm.py
quizzical/app/screens/main.py
quizzical/app/screens/quiz_maker.py
quizzical/app/screens/quiz_taker.py
quizzical/app/widgets/__init__.py
quizzical/app/widgets/answer.py
quizzical/app/widgets/answers.py
quizzical/app/widgets/logo.py
quizzical/app/widgets/question_counts.py
quizzical/app/widgets/quiz_list.py
quizzical/opentdb/__init__.py
quizzical/opentdb/category.py
quizzical/opentdb/client.py
quizzical/opentdb/counts.py
quizzical/opentdb/question.py
quizzical/opentdb/response.py
quizzical-0.2.1.dist-info/METADATA
quizzical-0.2.1.dist-info/WHEEL
quizzical-0.2.1.dist-info/entry_points.txt
quizzical-0.2.1.dist-info/licenses/LICENSE
quizzical-0.2.1.dist-info/RECORD
