Metadata-Version: 2.3
Name: quizzical
Version: 0.2.1
Summary: A trivia quiz game for the terminal
Project-URL: Homepage, https://github.com/davep/quizzical
Project-URL: Repository, https://github.com/davep/quizzical
Project-URL: Documentation, https://github.com/davep/quizzical/blob/main/README.md
Project-URL: Source, https://github.com/davep/quizzical
Project-URL: Issues, https://github.com/davep/quizzical/issues
Project-URL: Discussions, https://github.com/davep/quizzical/discussions
Author-email: Dave Pearson <davep@davep.org>
License: License :: OSI Approved :: GNU General Public License v3 or later (GPLv3+)
Classifier: Development Status :: 4 - Beta
Classifier: Environment :: Console
Classifier: Intended Audience :: End Users/Desktop
Classifier: License :: OSI Approved :: GNU General Public License v3 or later (GPLv3+)
Classifier: Natural Language :: English
Classifier: Operating System :: OS Independent
Classifier: Programming Language :: Python :: 3.12
Classifier: Programming Language :: Python :: 3.13
Classifier: Topic :: Games/Entertainment
Classifier: Topic :: Internet
Classifier: Topic :: Terminals
Classifier: Typing :: Typed
Requires-Python: >=3.12
Requires-Dist: httpx>=0.27.2
Requires-Dist: humanize>=4.11.0
Requires-Dist: textual-countdown>=0.1.1
Requires-Dist: textual>=0.86.3
Requires-Dist: xdg-base-dirs>=6.0.2
